cognitum/__init__.py
cognitum/dataset.py
cognitum/exceptions.py
cognitum/model.py
cognitum/types.py
cognitum-0.0.1.dev2.dist-info/METADATA
cognitum-0.0.1.dev2.dist-info/WHEEL
cognitum-0.0.1.dev2.dist-info/licenses/LICENSE
cognitum-0.0.1.dev2.dist-info/RECORD
