Metadata-Version: 2.3
Name: cognitum
Version: 0.0.1.dev2
Summary: A Python library for classifying free-text poll responses using large language models (LLMs).
Project-URL: Homepage, https://github.com/finnless/cognitum
Project-URL: Issues, https://github.com/finnless/cognitum/issues
Author-email: Nolan Windham <nolanwindham@gmail.com>
Classifier: License :: OSI Approved :: MIT License
Classifier: Operating System :: OS Independent
Classifier: Programming Language :: Python :: 3
Requires-Python: >=3.10
Requires-Dist: huggingface-hub[cli]
Requires-Dist: llama-cpp-python[server]
Requires-Dist: lmql[hf]
Requires-Dist: torch
Requires-Dist: torchvision
